tkviews/__init__.py
tkviews/app.py
tkviews/canvas.py
tkviews/listbox.py
tkviews/styles.py
tkviews/core/__init__.py
tkviews/core/rendering.py
tkviews/widgets/__init__.py
tkviews/widgets/binding.py
tkviews/widgets/node.py
tkviews/widgets/setters.py
tkviews/widgets/ttk.py
tkviews-4.0.0.dist-info/LICENSE
tkviews-4.0.0.dist-info/METADATA
tkviews-4.0.0.dist-info/WHEEL
tkviews-4.0.0.dist-info/top_level.txt
tkviews-4.0.0.dist-info/RECORD
