Metadata-Version: 2.1
Name: tkviews
Version: 4.0.0
Summary: Package for creating tkinter applications in declarative way.
Project-URL: Homepage, https://github.com/eumis/tkviews
Keywords: binding,tkinter,tk,tkviews,pyviews,python,mvvm,views
Classifier: Development Status :: 5 - Production/Stable
Classifier: Intended Audience :: Developers
Classifier: Topic :: Software Development :: Libraries
Classifier: License :: OSI Approved :: MIT License
Classifier: Programming Language :: Python :: 3
Classifier: Programming Language :: Python :: 3 :: Only
Classifier: Programming Language :: Python :: 3.6
Classifier: Programming Language :: Python :: 3.7
Classifier: Programming Language :: Python :: 3.8
Classifier: Programming Language :: Python :: 3.9
Classifier: Programming Language :: Python :: 3.10
Requires-Python: >=3.6
License-File: LICENSE
Requires-Dist: pyviews (==4.*)
